do_relative/__init__.py
do_relative/do_relative.py
do_relative-1.0.0.dist-info/METADATA
do_relative-1.0.0.dist-info/WHEEL
do_relative-1.0.0.dist-info/RECORD
