Metadata-Version: 2.4
Name: do-relative
Version: 1.0.0
Summary: Open and import relatively
Project-URL: Homepage, https://github.com/pyhacks/do-relative
Author-email: pyhacks <enginyildirim111@gmail.com>
Keywords: import,open,relative
